fastapi_core_config/__init__.py
fastapi_core_config/config.py
fastapi_core_config/repository.py
fastapi_core_config/security.py
rodrigo0000_fastapi_core_config-1.0.0.dist-info/METADATA
rodrigo0000_fastapi_core_config-1.0.0.dist-info/WHEEL
rodrigo0000_fastapi_core_config-1.0.0.dist-info/top_level.txt
rodrigo0000_fastapi_core_config-1.0.0.dist-info/RECORD
